{
  "cutechess": "cutechess-cli",
  "name": "external-gauntlet",
  "games": 20,
  "concurrency": 1,
  "tc": "8+0.08",
  "artifact_dir": ".tmp_matches",
  "opening_file": "nnue_openings.pgn",
  "opening_format": "pgn",
  "opening_order": "sequential",
  "opening_plies": 8,
  "engine_options": [
    "Hash=64",
    "Threads=1",
    "OwnBook=false"
  ],
  "opponents": [
    {
      "name": "Stockfish",
      "cmd": "C:/engines/stockfish/stockfish.exe",
      "rating": 3500,
      "options": [
        "Hash=64",
        "Threads=1"
      ]
    },
    {
      "name": "Berserk",
      "cmd": "C:/engines/berserk/berserk.exe",
      "rating": 3450,
      "options": [
        "Hash=64",
        "Threads=1"
      ]
    },
    {
      "name": "Ethereal",
      "cmd": "C:/engines/ethereal/ethereal.exe",
      "rating": 3350,
      "options": [
        "Hash=64",
        "Threads=1"
      ]
    }
  ]
}
